README.md
setup.py
sniffpy/__init__.py
sniffpy/constants.py
sniffpy/match.py
sniffpy/mimetype.py
sniffpy/ref.py
sniffpy/sniff.py
sniffpy/terminology.py
sniffpy/utils.py
sniffpy.egg-info/PKG-INFO
sniffpy.egg-info/SOURCES.txt
sniffpy.egg-info/dependency_links.txt
sniffpy.egg-info/top_level.txt
tests/__init__.py
tests/conftest.py
tests/resources.py
tests/test_match.py
tests/test_mimetype.py
tests/test_sniff.py