Metadata-Version: 2.1
Name: sniffpy
Version: 1.0.0
Summary: A package for mime-sniffing
Home-page: https://github.com/codeprentice-org/sniffpy
Author: Codeprentice
Author-email: nb2838@columbia.edu
License: UNKNOWN
Download-URL: https://github.com/woberton/sniffpy/archive/1.0.0.tar.gz
Platform: UNKNOWN
Classifier: Programming Language :: Python :: 3
Classifier: License :: OSI Approved :: MIT License
Classifier: Operating System :: OS Independent
Requires-Python: >=3.5
